bravado_django_test_client/__init__.py
bravado_django_test_client/config.py
bravado_django_test_client/django_test_client.py
bravado_django_test_client/__pycache__/__init__.cpython-37.pyc
bravado_django_test_client/__pycache__/config.cpython-37.pyc
bravado_django_test_client/__pycache__/django_test_client.cpython-37.pyc
bravado_django_test_client-1.0.1.dist-info/LICENSE
bravado_django_test_client-1.0.1.dist-info/METADATA
bravado_django_test_client-1.0.1.dist-info/WHEEL
bravado_django_test_client-1.0.1.dist-info/top_level.txt
bravado_django_test_client-1.0.1.dist-info/RECORD
