Metadata-Version: 2.1
Name: bravado-django-test-client
Version: 1.0.1
Summary: Bravado Django Test Client
Home-page: https://github.com/maximilianhurl/bravado-django-test-client
Author: Max Hurl
Author-email: max@maxhurl.co.uk
License: MIT
Platform: UNKNOWN
Classifier: Development Status :: 3 - Alpha
Classifier: Environment :: Web Environment
Classifier: Intended Audience :: Developers
Classifier: License :: OSI Approved :: MIT License
Classifier: Operating System :: OS Independent
Classifier: Topic :: Internet :: WWW/HTTP
Classifier: Programming Language :: Python :: 3
Classifier: Programming Language :: Python :: 3 :: Only
Classifier: Programming Language :: Python :: 3.5
Classifier: Programming Language :: Python :: 3.6
Requires-Dist: django
Requires-Dist: bravado
